{
    "save_dir": "Output_Images/",
    "save_name": "4_1_1_bat_img32",
    "params": {
        "background": {
            "color": [
                230,
                235,
                209,
                255
            ],
            "width": 1080,
            "height": 1080
        },
        "scale": {
            "dist": "T",
            "params": [
                0.66,
                0.81,
                0.96
            ]
        },
        "rotation": {
            "dist": "U",
            "params": [
                0,
                365
            ]
        },
        "color": {
            "dist": "M",
            "args": [
                [
                    31,
                    28,
                    28,
                    200
                ],
                [
                    20,
                    92,
                    163,
                    200
                ],
                [
                    20,
                    92,
                    163,
                    150
                ],
                [
                    20,
                    92,
                    163,
                    100
                ],
                [
                    89,
                    135,
                    28,
                    200
                ],
                [
                    89,
                    135,
                    28,
                    150
                ],
                [
                    89,
                    135,
                    28,
                    100
                ],
                [
                    196,
                    130,
                    23,
                    200
                ],
                [
                    196,
                    130,
                    23,
                    150
                ],
                [
                    196,
                    130,
                    23,
                    100
                ],
                [
                    0,
                    0,
                    0,
                    255
                ]
            ]
        },
        "centers": {
            "r": 160,
            "k": 32
        }
    },
    "find_images": [
        {
            "name": "bat-5.gif",
            "depth": 0.5
        }
    ],
    "excluded_images": [
        {
            "name": "bat-1.gif"
        },
        {
            "name": "bat-2.gif"
        },
        {
            "name": "bat-3.gif"
        },
        {
            "name": "bat-4.gif"
        },
        {
            "name": "bat-5.gif"
        },
        {
            "name": "bat-6.gif"
        },
        {
            "name": "bat-7.gif"
        },
        {
            "name": "bat-8.gif"
        },
        {
            "name": "bat-9.gif"
        },
        {
            "name": "bat-10.gif"
        },
        {
            "name": "bat-11.gif"
        },
        {
            "name": "bat-12.gif"
        },
        {
            "name": "bat-13.gif"
        },
        {
            "name": "bat-14.gif"
        },
        {
            "name": "bat-15.gif"
        },
        {
            "name": "bat-16.gif"
        },
        {
            "name": "bat-17.gif"
        },
        {
            "name": "bat-18.gif"
        },
        {
            "name": "bat-19.gif"
        },
        {
            "name": "bat-20.gif"
        }
    ],
    "results": {
        "0": {
            "imageDir": "Glas-4.gif",
            "center": [
                1054.4595980091178,
                423.8226087137303
            ],
            "scale": 0.7170232379015116,
            "rotation": 28.048800349821416,
            "color": [
                89,
                135,
                28,
                200
            ]
        },
        "1": {
            "imageDir": "device4-11.gif",
            "center": [
                985.9794250411402,
                270.4782546162937
            ],
            "scale": 0.8114170643957118,
            "rotation": 72.55760778210303,
            "color": [
                89,
                135,
                28,
                100
            ]
        },
        "2": {
            "imageDir": "device5-19.gif",
            "center": [
                815.9256609122169,
                124.72985339574313
            ],
            "scale": 0.8132587344693747,
            "rotation": 178.71678786080184,
            "color": [
                196,
                130,
                23,
                100
            ]
        },
        "3": {
            "imageDir": "Comma-18.gif",
            "center": [
                888.0749292171198,
                418.9096301697876
            ],
            "scale": 0.7743694441900397,
            "rotation": 96.22302895037315,
            "color": [
                196,
                130,
                23,
                100
            ]
        },
        "4": {
            "imageDir": "cup-18.gif",
            "center": [
                1000.9095701737652,
                584.4141551572695
            ],
            "scale": 0.8509784997332189,
            "rotation": 288.74745744383046,
            "color": [
                89,
                135,
                28,
                150
            ]
        },
        "5": {
            "imageDir": "car-19.gif",
            "center": [
                825.3460796693564,
                622.0736999598313
            ],
            "scale": 0.848503806648574,
            "rotation": 235.98799246619916,
            "color": [
                20,
                92,
                163,
                100
            ]
        },
        "6": {
            "imageDir": "teddy-14.gif",
            "center": [
                794.9270222641042,
                803.334674626993
            ],
            "scale": 0.7819602749939278,
            "rotation": 292.13320453669945,
            "color": [
                196,
                130,
                23,
                150
            ]
        },
        "7": {
            "imageDir": "device0-7.gif",
            "center": [
                961.1237723386204,
                23.99240935696983
            ],
            "scale": 0.752008956486412,
            "rotation": 8.424588838380489,
            "color": [
                196,
                130,
                23,
                150
            ]
        },
        "8": {
            "imageDir": "device3-9.gif",
            "center": [
                734.8388254394063,
                315.8062866125493
            ],
            "scale": 0.7666637104966894,
            "rotation": 75.22246885202576,
            "color": [
                89,
                135,
                28,
                200
            ]
        },
        "9": {
            "imageDir": "cattle-2.gif",
            "center": [
                649.9283456831038,
                1011.1677539813597
            ],
            "scale": 0.8509831614179733,
            "rotation": 282.48627470627883,
            "color": [
                196,
                130,
                23,
                200
            ]
        },
        "10": {
            "imageDir": "guitar-6.gif",
            "center": [
                704.7375048331403,
                516.7005504564487
            ],
            "scale": 0.7179502807814409,
            "rotation": 132.10696769983397,
            "color": [
                20,
                92,
                163,
                150
            ]
        },
        "11": {
            "imageDir": "fish-20.gif",
            "center": [
                877.4315588373325,
                1074.9872546102292
            ],
            "scale": 0.8047668972248386,
            "rotation": 357.7017287501567,
            "color": [
                196,
                130,
                23,
                100
            ]
        },
        "12": {
            "imageDir": "rat-06.gif",
            "center": [
                469.15218961800883,
                554.5327545829941
            ],
            "scale": 0.7946242712498902,
            "rotation": 16.80391983050421,
            "color": [
                20,
                92,
                163,
                200
            ]
        },
        "13": {
            "imageDir": "cattle-15.gif",
            "center": [
                568.8644026138892,
                332.9272700946579
            ],
            "scale": 0.8472170882973672,
            "rotation": 178.122145520078,
            "color": [
                196,
                130,
                23,
                200
            ]
        },
        "14": {
            "imageDir": "cup-17.gif",
            "center": [
                688.7452002560117,
                11.680592977830791
            ],
            "scale": 0.8593264165903847,
            "rotation": 77.88456663433097,
            "color": [
                89,
                135,
                28,
                100
            ]
        },
        "15": {
            "imageDir": "rat-17.gif",
            "center": [
                509.1364916494075,
                166.3215889427646
            ],
            "scale": 0.7143483537666726,
            "rotation": 81.99168202909078,
            "color": [
                89,
                135,
                28,
                150
            ]
        },
        "16": {
            "imageDir": "teddy-18.gif",
            "center": [
                576.9537514188974,
                860.2353705671542
            ],
            "scale": 0.8580183493071172,
            "rotation": 113.51180350906752,
            "color": [
                20,
                92,
                163,
                150
            ]
        },
        "17": {
            "imageDir": "fountain-05.gif",
            "center": [
                1055.0566548992047,
                785.8571673194448
            ],
            "scale": 0.8048302502013739,
            "rotation": 223.99743420525525,
            "color": [
                31,
                28,
                28,
                200
            ]
        },
        "18": {
            "imageDir": "bat-5.gif",
            "center": [
                668.7064780582264,
                678.5720089678479
            ],
            "scale": 0.866334367384784,
            "rotation": 102.99681976546924,
            "color": [
                196,
                130,
                23,
                150
            ]
        },
        "19": {
            "imageDir": "apple-18.gif",
            "center": [
                262.18179448809815,
                214.5837270511379
            ],
            "scale": 0.7529021715996997,
            "rotation": 231.78238381945275,
            "color": [
                89,
                135,
                28,
                200
            ]
        },
        "20": {
            "imageDir": "face-10.gif",
            "center": [
                322.711394890198,
                759.7640028175557
            ],
            "scale": 0.7559895947209583,
            "rotation": 265.0928873890423,
            "color": [
                31,
                28,
                28,
                200
            ]
        },
        "21": {
            "imageDir": "flatfish-14.gif",
            "center": [
                965.3098879572665,
                929.3217692866817
            ],
            "scale": 0.7899911172791287,
            "rotation": 186.9575178238929,
            "color": [
                20,
                92,
                163,
                100
            ]
        },
        "22": {
            "imageDir": "dog-12.gif",
            "center": [
                274.29791107421374,
                404.75342176122115
            ],
            "scale": 0.8515450353693546,
            "rotation": 47.2320604792377,
            "color": [
                196,
                130,
                23,
                200
            ]
        },
        "23": {
            "imageDir": "spring-5.gif",
            "center": [
                338.63912332935973,
                6.229301385261834
            ],
            "scale": 0.766359308171668,
            "rotation": 133.81583384240307,
            "color": [
                89,
                135,
                28,
                100
            ]
        },
        "24": {
            "imageDir": "children-5.gif",
            "center": [
                114.38767088602972,
                5.366888677476604
            ],
            "scale": 0.8331211527245517,
            "rotation": 217.03299973089472,
            "color": [
                31,
                28,
                28,
                200
            ]
        },
        "25": {
            "imageDir": "fountain-16.gif",
            "center": [
                21.317890564580637,
                534.7153291173871
            ],
            "scale": 0.8569074431431347,
            "rotation": 186.44813596756117,
            "color": [
                20,
                92,
                163,
                200
            ]
        },
        "26": {
            "imageDir": "key-14.gif",
            "center": [
                93.58362773056214,
                333.07353783812135
            ],
            "scale": 0.7981993036437346,
            "rotation": 77.73637606336959,
            "color": [
                89,
                135,
                28,
                200
            ]
        },
        "27": {
            "imageDir": "flatfish-9.gif",
            "center": [
                191.24481532212286,
                609.3941705378264
            ],
            "scale": 0.8022050375851673,
            "rotation": 56.46432592032709,
            "color": [
                31,
                28,
                28,
                200
            ]
        },
        "28": {
            "imageDir": "fork-5.gif",
            "center": [
                90.24571223719609,
                764.6340621268995
            ],
            "scale": 0.8098041219581396,
            "rotation": 144.29550610853244,
            "color": [
                89,
                135,
                28,
                200
            ]
        },
        "29": {
            "imageDir": "Heart-8.gif",
            "center": [
                454.3382454278035,
                1046.8258039852815
            ],
            "scale": 0.8183213639103446,
            "rotation": 250.4533698686114,
            "color": [
                20,
                92,
                163,
                200
            ]
        },
        "30": {
            "imageDir": "lmfish-15.gif",
            "center": [
                61.45448961140848,
                980.1816949047475
            ],
            "scale": 0.8691803028555801,
            "rotation": 351.0475296872027,
            "color": [
                20,
                92,
                163,
                200
            ]
        },
        "31": {
            "imageDir": "brick-01.gif",
            "center": [
                320.58210929276316,
                925.3551092886744
            ],
            "scale": 0.8173300844164947,
            "rotation": 260.16356480500474,
            "color": [
                89,
                135,
                28,
                200
            ]
        },
        "32": {
            "imageDir": "carriage-13.gif",
            "center": [
                239.02619452411955,
                1074.6772315038793
            ],
            "scale": 0.7456107204726464,
            "rotation": 160.39769816985142,
            "color": [
                196,
                130,
                23,
                150
            ]
        },
        "33": {
            "imageDir": "horse-3.gif",
            "center": [
                404.510055514963,
                306.2565258204047
            ],
            "scale": 0.7254380578917017,
            "rotation": 276.81211039722973,
            "color": [
                196,
                130,
                23,
                150
            ]
        },
        "34": {
            "imageDir": "turtle-18.gif",
            "center": [
                15.239927375205525,
                145.3062504810244
            ],
            "scale": 0.7649769098360826,
            "rotation": 253.4194964364727,
            "color": [
                20,
                92,
                163,
                100
            ]
        }
    }
}