{
    "save_dir": "Output_Images/",
    "save_name": "4_1_0_bat_img10",
    "params": {
        "background": {
            "color": [
                230,
                235,
                209,
                255
            ],
            "width": 1080,
            "height": 1080
        },
        "scale": {
            "dist": "T",
            "params": [
                0.25,
                0.4,
                0.55
            ]
        },
        "rotation": {
            "dist": "U",
            "params": [
                0,
                365
            ]
        },
        "color": {
            "dist": "M",
            "args": [
                [
                    31,
                    28,
                    28,
                    200
                ],
                [
                    20,
                    92,
                    163,
                    200
                ],
                [
                    20,
                    92,
                    163,
                    150
                ],
                [
                    20,
                    92,
                    163,
                    100
                ],
                [
                    89,
                    135,
                    28,
                    200
                ],
                [
                    89,
                    135,
                    28,
                    150
                ],
                [
                    89,
                    135,
                    28,
                    100
                ],
                [
                    196,
                    130,
                    23,
                    200
                ],
                [
                    196,
                    130,
                    23,
                    150
                ],
                [
                    196,
                    130,
                    23,
                    100
                ],
                [
                    0,
                    0,
                    0,
                    255
                ]
            ]
        },
        "centers": {
            "r": 120,
            "k": 32
        }
    },
    "find_images": [],
    "excluded_images": [
        {
            "name": "bat-1.gif"
        },
        {
            "name": "bat-2.gif"
        },
        {
            "name": "bat-3.gif"
        },
        {
            "name": "bat-4.gif"
        },
        {
            "name": "bat-5.gif"
        },
        {
            "name": "bat-6.gif"
        },
        {
            "name": "bat-7.gif"
        },
        {
            "name": "bat-8.gif"
        },
        {
            "name": "bat-9.gif"
        },
        {
            "name": "bat-10.gif"
        },
        {
            "name": "bat-11.gif"
        },
        {
            "name": "bat-12.gif"
        },
        {
            "name": "bat-13.gif"
        },
        {
            "name": "bat-14.gif"
        },
        {
            "name": "bat-15.gif"
        },
        {
            "name": "bat-16.gif"
        },
        {
            "name": "bat-17.gif"
        },
        {
            "name": "bat-18.gif"
        },
        {
            "name": "bat-19.gif"
        },
        {
            "name": "bat-20.gif"
        }
    ],
    "results": {
        "0": {
            "imageDir": "cellular_phone-17.gif",
            "center": [
                796.804538576631,
                1057.739739839345
            ],
            "scale": 0.377676114214928,
            "rotation": 62.88799108417319,
            "color": [
                89,
                135,
                28,
                200
            ]
        },
        "1": {
            "imageDir": "bell-12.gif",
            "center": [
                924.4067096420065,
                976.4771518325228
            ],
            "scale": 0.37991246587118976,
            "rotation": 359.9035949960555,
            "color": [
                20,
                92,
                163,
                100
            ]
        },
        "2": {
            "imageDir": "Bone-8.gif",
            "center": [
                832.1033174492625,
                855.6009246460028
            ],
            "scale": 0.38865922074067194,
            "rotation": 164.14899400664444,
            "color": [
                196,
                130,
                23,
                200
            ]
        },
        "3": {
            "imageDir": "truck-05.gif",
            "center": [
                706.7773722806407,
                801.0151558384816
            ],
            "scale": 0.4602840362821705,
            "rotation": 235.18257207000457,
            "color": [
                89,
                135,
                28,
                150
            ]
        },
        "4": {
            "imageDir": "Glas-8.gif",
            "center": [
                1035.9650966988158,
                906.9222279239708
            ],
            "scale": 0.3477427264956353,
            "rotation": 287.1805235425249,
            "color": [
                89,
                135,
                28,
                100
            ]
        },
        "5": {
            "imageDir": "device6-3.gif",
            "center": [
                753.6595008553111,
                626.810627275134
            ],
            "scale": 0.43019474721191053,
            "rotation": 289.90475419607475,
            "color": [
                20,
                92,
                163,
                200
            ]
        },
        "6": {
            "imageDir": "device2-3.gif",
            "center": [
                545.6318243050915,
                687.2397287478515
            ],
            "scale": 0.37415119843430034,
            "rotation": 102.52446004372209,
            "color": [
                31,
                28,
                28,
                200
            ]
        },
        "7": {
            "imageDir": "device6-9.gif",
            "center": [
                955.477463827064,
                810.8918772659458
            ],
            "scale": 0.3583648463108267,
            "rotation": 319.8015764320208,
            "color": [
                20,
                92,
                163,
                100
            ]
        },
        "8": {
            "imageDir": "Misk-16.gif",
            "center": [
                944.2877252600865,
                652.8156913328869
            ],
            "scale": 0.4356812325293142,
            "rotation": 5.894991813408436,
            "color": [
                196,
                130,
                23,
                150
            ]
        },
        "9": {
            "imageDir": "crown-9.gif",
            "center": [
                1079.9298958825461,
                720.5700163939609
            ],
            "scale": 0.37409869035411414,
            "rotation": 271.21740618515975,
            "color": [
                89,
                135,
                28,
                150
            ]
        },
        "10": {
            "imageDir": "bell-14.gif",
            "center": [
                910.7999876881574,
                471.67106065535927
            ],
            "scale": 0.41428881453998384,
            "rotation": 161.57294298831613,
            "color": [
                196,
                130,
                23,
                150
            ]
        },
        "11": {
            "imageDir": "shoe-6.gif",
            "center": [
                638.1764509958509,
                941.5845349642666
            ],
            "scale": 0.3656848635188935,
            "rotation": 264.9895533611831,
            "color": [
                196,
                130,
                23,
                200
            ]
        },
        "12": {
            "imageDir": "horse-15.gif",
            "center": [
                715.620106539616,
                432.94106373764146
            ],
            "scale": 0.4457227077260344,
            "rotation": 359.3770093377619,
            "color": [
                89,
                135,
                28,
                200
            ]
        },
        "13": {
            "imageDir": "hat-2.gif",
            "center": [
                1077.471548613584,
                1030.0462097144812
            ],
            "scale": 0.3795009856524344,
            "rotation": 268.2538276736606,
            "color": [
                89,
                135,
                28,
                100
            ]
        },
        "14": {
            "imageDir": "car-08.gif",
            "center": [
                521.6346408817493,
                827.5367309710548
            ],
            "scale": 0.4490704901150664,
            "rotation": 130.54814324799838,
            "color": [
                89,
                135,
                28,
                100
            ]
        },
        "15": {
            "imageDir": "flatfish-14.gif",
            "center": [
                834.085832070529,
                725.1498838619186
            ],
            "scale": 0.424188901699582,
            "rotation": 249.4948340540277,
            "color": [
                20,
                92,
                163,
                200
            ]
        },
        "16": {
            "imageDir": "fish-17.gif",
            "center": [
                1023.7569011557721,
                516.8055903624047
            ],
            "scale": 0.3686243845292617,
            "rotation": 227.50933021276109,
            "color": [
                20,
                92,
                163,
                150
            ]
        },
        "17": {
            "imageDir": "lmfish-4.gif",
            "center": [
                619.7087757557563,
                526.9052437976891
            ],
            "scale": 0.41981788496815764,
            "rotation": 328.79449306907503,
            "color": [
                20,
                92,
                163,
                100
            ]
        },
        "18": {
            "imageDir": "dog-4.gif",
            "center": [
                424.75669241768173,
                538.2434049979183
            ],
            "scale": 0.4205824380207251,
            "rotation": 134.18474802716182,
            "color": [
                196,
                130,
                23,
                150
            ]
        },
        "19": {
            "imageDir": "stef-07.gif",
            "center": [
                374.49337813909307,
                671.805014846148
            ],
            "scale": 0.2944604398478464,
            "rotation": 8.440729420220444,
            "color": [
                20,
                92,
                163,
                150
            ]
        },
        "20": {
            "imageDir": "cattle-2.gif",
            "center": [
                796.4413160141737,
                219.75970938451215
            ],
            "scale": 0.37670529067962855,
            "rotation": 154.10003085090995,
            "color": [
                89,
                135,
                28,
                150
            ]
        },
        "21": {
            "imageDir": "device0-1.gif",
            "center": [
                518.2588224647116,
                997.9393712200126
            ],
            "scale": 0.42970409215909317,
            "rotation": 81.31542560646452,
            "color": [
                89,
                135,
                28,
                200
            ]
        },
        "22": {
            "imageDir": "Comma-2.gif",
            "center": [
                294.71017349461454,
                545.0961361944419
            ],
            "scale": 0.4347089545943305,
            "rotation": 138.47250214548114,
            "color": [
                89,
                135,
                28,
                150
            ]
        },
        "23": {
            "imageDir": "personal_car-13.gif",
            "center": [
                380.21675041188877,
                988.9142133724197
            ],
            "scale": 0.45566344401092074,
            "rotation": 287.4291351450531,
            "color": [
                89,
                135,
                28,
                200
            ]
        },
        "24": {
            "imageDir": "fly-2.gif",
            "center": [
                224.8247201887313,
                800.8896180394162
            ],
            "scale": 0.3514083693335265,
            "rotation": 273.6488009398641,
            "color": [
                196,
                130,
                23,
                200
            ]
        },
        "25": {
            "imageDir": "face-5.gif",
            "center": [
                930.3043376605171,
                200.87226188722923
            ],
            "scale": 0.32311693407592196,
            "rotation": 311.932914696984,
            "color": [
                196,
                130,
                23,
                150
            ]
        },
        "26": {
            "imageDir": "teddy-14.gif",
            "center": [
                1060.623428784865,
                375.8496775005359
            ],
            "scale": 0.33068685704977974,
            "rotation": 220.15388937231626,
            "color": [
                89,
                135,
                28,
                100
            ]
        },
        "27": {
            "imageDir": "beetle-5.gif",
            "center": [
                191.71746757533404,
                1030.354224806952
            ],
            "scale": 0.41059975333640986,
            "rotation": 255.26871157918868,
            "color": [
                31,
                28,
                28,
                200
            ]
        },
        "28": {
            "imageDir": "children-8.gif",
            "center": [
                33.77902010148995,
                923.2889341174932
            ],
            "scale": 0.34497028165432,
            "rotation": 249.95612629581066,
            "color": [
                196,
                130,
                23,
                100
            ]
        },
        "29": {
            "imageDir": "hat-17.gif",
            "center": [
                556.1146991507775,
                358.73735027218294
            ],
            "scale": 0.4199405804161601,
            "rotation": 182.06059656897838,
            "color": [
                20,
                92,
                163,
                200
            ]
        },
        "30": {
            "imageDir": "dog-14.gif",
            "center": [
                305.5706145767618,
                368.78831888309026
            ],
            "scale": 0.40788943219143964,
            "rotation": 317.3067312983691,
            "color": [
                20,
                92,
                163,
                100
            ]
        },
        "31": {
            "imageDir": "device8-11.gif",
            "center": [
                363.1389056514375,
                814.3775583161455
            ],
            "scale": 0.37924498499623155,
            "rotation": 6.344245288509484,
            "color": [
                89,
                135,
                28,
                100
            ]
        },
        "32": {
            "imageDir": "pocket-19.gif",
            "center": [
                922.9895710268721,
                331.19823028452555
            ],
            "scale": 0.4107168986401731,
            "rotation": 328.00322099737946,
            "color": [
                20,
                92,
                163,
                100
            ]
        },
        "33": {
            "imageDir": "sea_snake-18.gif",
            "center": [
                655.5328846132035,
                1075.3656992205326
            ],
            "scale": 0.45769956139623674,
            "rotation": 302.6740186700196,
            "color": [
                89,
                135,
                28,
                150
            ]
        },
        "34": {
            "imageDir": "cellular_phone-12.gif",
            "center": [
                158.89625853522762,
                637.734604746031
            ],
            "scale": 0.3903096968077999,
            "rotation": 26.928108095321296,
            "color": [
                20,
                92,
                163,
                150
            ]
        },
        "35": {
            "imageDir": "rat-06.gif",
            "center": [
                145.1039958353073,
                503.4373426311554
            ],
            "scale": 0.4358043450505543,
            "rotation": 312.23277242334103,
            "color": [
                89,
                135,
                28,
                100
            ]
        },
        "36": {
            "imageDir": "device8-14.gif",
            "center": [
                441.8819713628959,
                303.17147988053046
            ],
            "scale": 0.2608517794108741,
            "rotation": 134.0899979697824,
            "color": [
                89,
                135,
                28,
                150
            ]
        },
        "37": {
            "imageDir": "key-11.gif",
            "center": [
                141.68750399253122,
                381.17164427072476
            ],
            "scale": 0.38573448805946564,
            "rotation": 220.71056413873086,
            "color": [
                89,
                135,
                28,
                100
            ]
        },
        "38": {
            "imageDir": "Glas-9.gif",
            "center": [
                271.2802223073552,
                916.1369660823598
            ],
            "scale": 0.29196603112659314,
            "rotation": 16.14408344027602,
            "color": [
                31,
                28,
                28,
                200
            ]
        },
        "39": {
            "imageDir": "horse-12.gif",
            "center": [
                146.19815424183858,
                253.07332003853094
            ],
            "scale": 0.3413125308177342,
            "rotation": 26.72967931704466,
            "color": [
                89,
                135,
                28,
                100
            ]
        },
        "40": {
            "imageDir": "hat-16.gif",
            "center": [
                676.5238866483992,
                229.97622461824588
            ],
            "scale": 0.37485789637636135,
            "rotation": 191.1547235426785,
            "color": [
                31,
                28,
                28,
                200
            ]
        },
        "41": {
            "imageDir": "teddy-15.gif",
            "center": [
                72.19530412217226,
                791.313443195438
            ],
            "scale": 0.3719361542899239,
            "rotation": 230.31948125278535,
            "color": [
                196,
                130,
                23,
                200
            ]
        },
        "42": {
            "imageDir": "butterfly-19.gif",
            "center": [
                36.763766114215,
                610.5358656562983
            ],
            "scale": 0.36168837621223593,
            "rotation": 279.2619626224488,
            "color": [
                20,
                92,
                163,
                150
            ]
        },
        "43": {
            "imageDir": "frog-17.gif",
            "center": [
                282.12696318339044,
                221.22267414457687
            ],
            "scale": 0.3189465856591373,
            "rotation": 20.8559362458241,
            "color": [
                31,
                28,
                28,
                200
            ]
        },
        "44": {
            "imageDir": "truck-01.gif",
            "center": [
                824.702090262542,
                82.13236062855893
            ],
            "scale": 0.45129993601410057,
            "rotation": 92.84633315511897,
            "color": [
                196,
                130,
                23,
                150
            ]
        },
        "45": {
            "imageDir": "bell-7.gif",
            "center": [
                1044.0001318609886,
                160.06169617883455
            ],
            "scale": 0.359445819828254,
            "rotation": 340.1729672781539,
            "color": [
                20,
                92,
                163,
                200
            ]
        },
        "46": {
            "imageDir": "device0-6.gif",
            "center": [
                478.4941018782989,
                96.02280104128656
            ],
            "scale": 0.29560999040556596,
            "rotation": 342.0616455090144,
            "color": [
                89,
                135,
                28,
                150
            ]
        },
        "47": {
            "imageDir": "sea_snake-16.gif",
            "center": [
                960.5718227854275,
                70.70078154209327
            ],
            "scale": 0.3927204937319748,
            "rotation": 72.37023156453051,
            "color": [
                196,
                130,
                23,
                100
            ]
        },
        "48": {
            "imageDir": "device8-5.gif",
            "center": [
                701.146644654159,
                10.860911762480313
            ],
            "scale": 0.4413719126307668,
            "rotation": 181.83740218198054,
            "color": [
                31,
                28,
                28,
                200
            ]
        },
        "49": {
            "imageDir": "cellular_phone-14.gif",
            "center": [
                363.54889931804763,
                11.666333149917278
            ],
            "scale": 0.3471724394039112,
            "rotation": 127.27445513209517,
            "color": [
                196,
                130,
                23,
                200
            ]
        },
        "50": {
            "imageDir": "device9-20.gif",
            "center": [
                150.13230256677375,
                10.376754174281384
            ],
            "scale": 0.4564947268212366,
            "rotation": 167.28189437240772,
            "color": [
                196,
                130,
                23,
                150
            ]
        },
        "51": {
            "imageDir": "bell-9.gif",
            "center": [
                10.391328204199112,
                140.39881311347492
            ],
            "scale": 0.45250693876556125,
            "rotation": 76.04948550583835,
            "color": [
                89,
                135,
                28,
                200
            ]
        },
        "52": {
            "imageDir": "classic-9.gif",
            "center": [
                632.7317384724367,
                115.25030686403566
            ],
            "scale": 0.43664938916918866,
            "rotation": 228.316442621829,
            "color": [
                20,
                92,
                163,
                200
            ]
        },
        "53": {
            "imageDir": "Comma-13.gif",
            "center": [
                17.452969249820228,
                8.689325242182534
            ],
            "scale": 0.28373411083459926,
            "rotation": 351.25205244123606,
            "color": [
                196,
                130,
                23,
                100
            ]
        },
        "54": {
            "imageDir": "butterfly-8.gif",
            "center": [
                6.400013367517403,
                294.97753549793885
            ],
            "scale": 0.36395631764611197,
            "rotation": 354.1308119576635,
            "color": [
                20,
                92,
                163,
                100
            ]
        },
        "55": {
            "imageDir": "dog-3.gif",
            "center": [
                194.2948972245094,
                135.0211278220224
            ],
            "scale": 0.3582832520194761,
            "rotation": 67.10006446206918,
            "color": [
                20,
                92,
                163,
                100
            ]
        },
        "56": {
            "imageDir": "HCircle-16.gif",
            "center": [
                548.3142195215817,
                201.45569676771026
            ],
            "scale": 0.4582536428734335,
            "rotation": 55.70153999687619,
            "color": [
                89,
                135,
                28,
                150
            ]
        },
        "57": {
            "imageDir": "beetle-14.gif",
            "center": [
                34.38535096988417,
                1053.3266578327878
            ],
            "scale": 0.44098746865406346,
            "rotation": 22.77707674050221,
            "color": [
                89,
                135,
                28,
                200
            ]
        }
    }
}